vision_rl/__init__.py
vision_rl/register.py
vision_rl/core/__init__.py
vision_rl/core/mixins.py
vision_rl/core/visual_env.py
vision_rl/envs/__init__.py
vision_rl/envs/visual_cartpole.py
vision_rl/envs/visual_frozenlake.py
vision_rl/monitors/__init__.py
vision_rl/monitors/action_monitor.py
vision_rl/monitors/reward_monitor.py
vision_rl/ui/__init__.py
vision_rl/ui/callbacks.py
vision_rl/ui/dashboard.py
vision_rl/ui/viewer.py
vision_rl/utils/__init__.py
vision_rl/utils/cv_utils.py
vision_rl/utils/render_utils.py
vision_rl/wrappers/__init__.py
vision_rl/wrappers/frame_stack.py
vision_rl/wrappers/heatmap.py
vision_rl/wrappers/logger.py
vision_rl/wrappers/visual_obs.py
vision_rl-0.0.5.dist-info/licenses/LICENSE
vision_rl-0.0.5.dist-info/METADATA
vision_rl-0.0.5.dist-info/WHEEL
vision_rl-0.0.5.dist-info/top_level.txt
vision_rl-0.0.5.dist-info/RECORD
