Metadata-Version: 2.4
Name: vision_rl
Version: 0.0.5
Summary: Visual Reinforcement Learning tools
Author-email: User <user@example.com>
License-File: LICENSE
Requires-Dist: gymnasium
Requires-Dist: numpy
Requires-Dist: opencv-python
Requires-Dist: matplotlib
Dynamic: license-file
